resources/__init__.py
resources/images/1-grey.jpg
resources/images/1.jpg
resources/images/2-grey.jpg
resources/images/2.jpg
resources/images/3-grey.jpg
resources/images/3.jpg
resources/images/sample.jpg
roundface/__init__.py
roundface/__main__.py
roundface/roundface.py
roundface/model/__init__.py
roundface/model/deploy.prototxt
roundface/model/weights.caffemodel
roundface-0.0.17.dist-info/LICENSE
roundface-0.0.17.dist-info/METADATA
roundface-0.0.17.dist-info/WHEEL
roundface-0.0.17.dist-info/entry_points.txt
roundface-0.0.17.dist-info/top_level.txt
roundface-0.0.17.dist-info/RECORD
