Metadata-Version: 2.1
Name: roundface
Version: 0.0.17
Summary: Detect Faces In Images and Generate Profile Photos
Home-page: https://github.com/Edward-K1/roundface
Author: Edward Kigozi
License: UNKNOWN
Keywords: face detect roundface profile photo
Platform: UNKNOWN
Classifier: Programming Language :: Python :: 3
Classifier: License :: OSI Approved :: MIT License
Classifier: Operating System :: OS Independent
Requires-Python: >=3.6
